{"assets":{"416159004369F0DF0805411033AC076A":{"type":"texture","index":35,"assetRequest":{"type":"slide","state":"incoming","slide":"CF2FBC3B-9550-4A65-A652-316E02D44B6C"},"url":"assets/416159004369F0DF0805411033AC076A.svg","width":720,"height":540},"7909B8EDCB66E67859986292E53E631F":{"type":"texture","index":34,"assetRequest":{"type":"slide","state":"outgoing","slide":"3D3A77CA-9694-421A-9B50-38AB3622E769"},"url":"assets/7909B8EDCB66E67859986292E53E631F.svg","width":720,"height":540}},"events":[{"effects":[{"beginTime":0,"baseLayer":{"animations":[],"initialState":{"affineTransform":[1,0,0,1,0,0],"masksToBounds":true,"rotation":0,"scale":1,"position":{"pointX":360,"pointY":270},"width":720,"sublayerTransform":[1,0,0,0,0,1,0,0,0,0,1,0,0,0,0,1],"contentsRect":{"y":0,"x":0,"width":1,"height":1},"opacity":1,"edgeAntialiasingMask":0,"height":540,"hidden":false,"anchorPoint":{"pointX":0.5,"pointY":0.5}},"objectID":"0","layers":[{"animations":[],"initialState":{"affineTransform":[1,0,0,1,0,0],"masksToBounds":false,"rotation":0,"scale":1,"position":{"pointX":360,"pointY":270},"width":720,"sublayerTransform":[1,0,0,0,0,1,0,0,0,0,1,-0.0007001582493355197,0,0,0,1],"contentsRect":{"y":0,"x":0,"width":1,"height":1},"opacity":1,"edgeAntialiasingMask":15,"height":540,"hidden":false,"anchorPoint":{"pointX":0.5,"pointY":0.5}},"layers":[{"animations":[],"layers":[],"initialState":{"affineTransform":[1,0,0,1,0,0],"masksToBounds":false,"rotation":0,"scale":1,"position":{"pointX":360,"pointY":270},"width":720,"sublayerTransform":[1,0,0,0,0,1,0,0,0,0,1,0,0,0,0,1],"contentsRect":{"y":0,"x":0,"width":1,"height":1},"opacity":1,"edgeAntialiasingMask":0,"height":540,"hidden":false,"anchorPoint":{"pointX":0.5,"pointY":0.5}},"texture":"416159004369F0DF0805411033AC076A"},{"animations":[{"from":{"scalar":false},"beginTime":0,"repeatCount":0,"fillMode":"both","property":"hidden","duration":0.01,"to":{"scalar":true}}],"layers":[],"initialState":{"affineTransform":[1,0,0,1,0,0],"masksToBounds":false,"rotation":0,"scale":1,"position":{"pointX":360,"pointY":270},"width":720,"sublayerTransform":[1,0,0,0,0,1,0,0,0,0,1,0,0,0,0,1],"contentsRect":{"y":0,"x":0,"width":1,"height":1},"opacity":1,"edgeAntialiasingMask":0,"height":540,"hidden":false,"anchorPoint":{"pointX":0.5,"pointY":0.5}},"texture":"7909B8EDCB66E67859986292E53E631F"}]}]},"effects":[],"duration":0.01,"type":"transition","name":"none","objectID":"0"}],"automaticPlay":false,"hyperlinks":[],"accessibility":[{"text":"Width1 = Height1 = 2 pixels","targetRectangle":{"y":153.4113402366638,"x":217.6801543235779,"width":282.41259765625,"height":26}},{"text":"Small search area A1","targetRectangle":{"y":392.6683440208435,"x":314.6965403556824,"width":163.951171875,"height":21}},{"text":"Height1","targetRectangle":{"y":228.2406249046326,"x":343.0461440086365,"width":62.2353515625,"height":21}},{"text":"Search area is reduced in order to apply interpolation","targetRectangle":{"y":466.3773131370544,"x":170.8226714134216,"width":423.0615234375,"height":21}},{"text":"Width1","targetRectangle":{"y":312.5577940940857,"x":441.6975646018982,"width":57.5947265625,"height":21}},{"text":"4) Displacement measurements","targetRectangle":{"y":54.51212453842163,"x":2.58732271194458,"width":499.341796875,"height":40}},{"text":"Moved","targetRectangle":{"y":296.279679775238,"x":324.5398785979851,"width":54.369140625,"height":21}},{"text":"template","targetRectangle":{"y":317.279679775238,"x":316.6297223479851,"width":70.189453125,"height":21}}],"baseLayer":{"animations":[],"initialState":{"affineTransform":[1,0,0,1,0,0],"masksToBounds":true,"rotation":0,"scale":1,"position":{"pointX":360,"pointY":270},"width":720,"sublayerTransform":[1,0,0,0,0,1,0,0,0,0,1,0,0,0,0,1],"contentsRect":{"y":0,"x":0,"width":1,"height":1},"opacity":1,"edgeAntialiasingMask":0,"height":540,"hidden":false,"anchorPoint":{"pointX":0.5,"pointY":0.5}},"objectID":"0","layers":[{"animations":[],"initialState":{"affineTransform":[1,0,0,1,0,0],"masksToBounds":false,"rotation":0,"scale":1,"position":{"pointX":360,"pointY":270},"width":720,"sublayerTransform":[1,0,0,0,0,1,0,0,0,0,1,-0.0007001582493355197,0,0,0,1],"contentsRect":{"y":0,"x":0,"width":1,"height":1},"opacity":1,"edgeAntialiasingMask":15,"height":540,"hidden":false,"anchorPoint":{"pointX":0.5,"pointY":0.5}},"layers":[{"animations":[],"layers":[],"initialState":{"affineTransform":[1,0,0,1,0,0],"masksToBounds":false,"rotation":0,"scale":1,"position":{"pointX":360,"pointY":270},"width":720,"sublayerTransform":[1,0,0,0,0,1,0,0,0,0,1,0,0,0,0,1],"contentsRect":{"y":0,"x":0,"width":1,"height":1},"opacity":1,"edgeAntialiasingMask":0,"height":540,"hidden":false,"anchorPoint":{"pointX":0.5,"pointY":0.5}},"texture":"7909B8EDCB66E67859986292E53E631F"}]}]}}]}